unmanic_api/__init__.py
unmanic_api/__version__.py
unmanic_api/client.py
unmanic_api/exceptions.py
unmanic_api/models.py
unmanic_api/unmanic.py
unmanic_api-0.0.5.dist-info/LICENSE
unmanic_api-0.0.5.dist-info/METADATA
unmanic_api-0.0.5.dist-info/WHEEL
unmanic_api-0.0.5.dist-info/top_level.txt
unmanic_api-0.0.5.dist-info/RECORD
